mcp_applemusic.py
mcp_applemusic_fastmcp-0.1.6.dist-info/licenses/LICENSE
mcp_applemusic_fastmcp-0.1.6.dist-info/METADATA
mcp_applemusic_fastmcp-0.1.6.dist-info/WHEEL
mcp_applemusic_fastmcp-0.1.6.dist-info/entry_points.txt
mcp_applemusic_fastmcp-0.1.6.dist-info/top_level.txt
mcp_applemusic_fastmcp-0.1.6.dist-info/RECORD
