Metadata-Version: 2.4
Name: mcp-applemusic-fastmcp
Version: 0.1.6
Summary: A simple Apple Music API client for MCP
Project-URL: Homepage, https://github.com/fastmcp-me/mcp-applemusic#readme
Project-URL: Repository, https://github.com/fastmcp-me/mcp-applemusic.git
Project-URL: Issues, https://github.com/fastmcp-me/mcp-applemusic/issues
Requires-Python: >=3.13
License-File: LICENSE
Requires-Dist: mcp>=1.2.1
Dynamic: license-file
